AdobeConnect2Video/__init__.py
AdobeConnect2Video/__main__.py
AdobeConnect2Video/adobe_connect_2_video.py
AdobeConnect2Video/no_video.jpg
AdobeConnect2Video/utilities.py
AdobeConnect2Video-1.2.1.dist-info/LICENSE
AdobeConnect2Video-1.2.1.dist-info/METADATA
AdobeConnect2Video-1.2.1.dist-info/WHEEL
AdobeConnect2Video-1.2.1.dist-info/entry_points.txt
AdobeConnect2Video-1.2.1.dist-info/top_level.txt
AdobeConnect2Video-1.2.1.dist-info/RECORD
