Metadata-Version: 2.1
Name: AdobeConnect2Video
Version: 1.2.1
Summary: A handy tool to convert adobe connect zip data into a single video file
Home-page: https://github.com/AliRezaBeigy/AdobeConnect2Video
Author: AliReza Beigy
Author-email: AliRezaBeigyKhu@gmail.com
License: MIT
Keywords: adobe-connect ffmpeg
Platform: nt
Platform: posix
Classifier: Development Status :: 5 - Production/Stable
Classifier: Programming Language :: Python :: 3
Classifier: Programming Language :: Python :: 3.3
Classifier: Programming Language :: Python :: 3.4
Classifier: Programming Language :: Python :: 3.5
Classifier: Programming Language :: Python :: 3.6
Classifier: License :: OSI Approved :: MIT License
Requires-Python: >=3.6
License-File: LICENSE
Requires-Dist: untangle
